sdypy/excitation/__init__.py
sdypy_excitation-0.1.1.dist-info/METADATA
sdypy_excitation-0.1.1.dist-info/WHEEL
sdypy_excitation-0.1.1.dist-info/licenses/License
sdypy_excitation-0.1.1.dist-info/RECORD
