Metadata-Version: 2.1
Name: sdypy-excitation
Version: 0.1.1
Summary: Excitation signals as used in structural dynamics and vibration fatigue.
Project-URL: homepage, https://github.com/sdypy/sdypy-excitation
Project-URL: documentation, https://pyexsi.readthedocs.io/en/latest/index.html
Project-URL: source, https://github.com/sdypy/sdypy-excitation
Author-email: "Janko Slavič et al." <janko.slavic@fs.uni-lj.si>
Maintainer-email: "Janko Slavič et al." <janko.slavic@fs.uni-lj.si>
License-Expression: MIT
License-File: License
Keywords: excitation signals,structural dynamics,vibration fatigue
Classifier: Development Status :: 5 - Production/Stable
Classifier: Intended Audience :: Developers
Classifier: License :: OSI Approved :: MIT License
Classifier: Programming Language :: Python :: 3.10
Classifier: Topic :: Scientific/Engineering
Requires-Python: >=3.10
Requires-Dist: pyexsi
Provides-Extra: dev
Requires-Dist: build; extra == 'dev'
Requires-Dist: pytest; extra == 'dev'
Requires-Dist: sphinx; extra == 'dev'
Requires-Dist: sphinx-copybutton>=0.5.2; extra == 'dev'
Requires-Dist: sphinx-rtd-theme; extra == 'dev'
Requires-Dist: twine; extra == 'dev'
Requires-Dist: wheel; extra == 'dev'
